patentfield_client/__init__.py
patentfield_client/client.py
patentfield_client/py.typed
patentfield_client-0.1.0.dist-info/WHEEL
patentfield_client-0.1.0.dist-info/METADATA
patentfield_client-0.1.0.dist-info/RECORD
