Metadata-Version: 2.3
Name: patentfield-client
Version: 0.1.0
Summary: Add your description here
Author: neka-nat
Author-email: neka-nat <nekanat.stock@gmail.com>
Requires-Dist: httpx>=0.28.1
Requires-Dist: pillow>=11.3.0
Requires-Dist: python-dotenv>=1.1.1
Requires-Python: >=3.13
